pynotio/__init__.py
pynotio/blocks.py
pynotio/filters.py
pynotio/page.py
pynotio/pagelist.py
pynotio/properties.py
pynotio/richtext.py
pynotio/sorts.py
pynotio/version.py
pynotio/wrapper.py
pynotio-0.0.3.dist-info/LICENSE
pynotio-0.0.3.dist-info/METADATA
pynotio-0.0.3.dist-info/WHEEL
pynotio-0.0.3.dist-info/top_level.txt
pynotio-0.0.3.dist-info/RECORD
